{"success": true, "results": {"P.1": [{"date": "2021-09-21", "name": "Alabama", "id": "USA_US-AL", "total_count": 1, "lineage_count": 0, "cum_total_count": 2944, "cum_lineage_count": 2, "proportion": 0.0006793478260869565, "proportion_ci_lower": 0.00014119645859462406, "proportion_ci_upper": 0.0021776141536785643}, {"date": "2021-09-20", "name": "Alaska", "id": "USA_US-AK", "total_count": 1, "lineage_count": 0, "cum_total_count": 1863, "cum_lineage_count": 0, "proportion": 0.0, "proportion_ci_lower": 2.635365568038805e-07, "proportion_ci_upper": 0.001347243018447568}, {"date": "2021-09-23", "name": "Arizona", "id": "USA_US-AZ", "total_count": 1, "lineage_count": 0, "cum_total_count": 5807, "cum_lineage_count": 8, "proportion": 0.0013776476666092646, "proportion_ci_lower": 0.0006515076079243217, "proportion_ci_upper": 0.0025978359847230736}, {"date": "2021-09-14", "name": "Arkansas", "id": "USA_US-AR", "total_count": 1, "lineage_count": 0, "cum_total_count": 1994, "cum_lineage_count": 1, "proportion": 0.0005015045135406219, "proportion_ci_lower": 5.411647560635292e-05, "proportion_ci_upper": 0.002341681301019638}, {"date": "2021-09-23", "name": "California", "id": "USA_US-CA", "total_count": 23, "lineage_count": 0, "cum_total_count": 36904, "cum_lineage_count": 64, "proportion": 0.0017342293518317797, "proportion_ci_lower": 0.0013477097164130746, "proportion_ci_upper": 0.0021988444745926206}, {"date": "2021-09-21", "name": "Colorado", "id": "USA_US-CO", "total_count": 47, "lineage_count": 0, "cum_total_count": 5926, "cum_lineage_count": 0, "proportion": 0.0, "proportion_ci_lower": 8.285754698319523e-08, "proportion_ci_upper": 0.000423777396789946}, {"date": "2021-09-20", "name": "Connecticut", "id": "USA_US-CT", "total_count": 15, "lineage_count": 0, "cum_total_count": 3087, "cum_lineage_count": 2, "proportion": 0.0006478781988986071, "proportion_ci_lower": 0.0001346546245999286, "proportion_ci_upper": 0.0020768202205133646}, {"date": "2021-09-11", "name": "Delaware", "id": "USA_US-DE", "total_count": 3, "lineage_count": 0, "cum_total_count": 868, "cum_lineage_count": 1, "proportion": 0.001152073732718894, "proportion_ci_lower": 0.00012433412996597606, "proportion_ci_upper": 0.005372096024846118}, {"date": "2021-09-11", "name": "District of Columbia", "id": "USA_US-DC", "total_count": 1, "lineage_count": 0, "cum_total_count": 977, "cum_lineage_count": 3, "proportion": 0.0030706243602865915, "proportion_ci_lower": 0.0008655591709061983, "proportion_ci_upper": 0.00817180120797989}, {"date": "2021-09-20", "name": "Florida", "id": "USA_US-FL", "total_count": 1, "lineage_count": 0, "cum_total_count": 10643, "cum_lineage_count": 14, "proportion": 0.0013154185849854364, "proportion_ci_lower": 0.0007540732155342206, "proportion_ci_upper": 0.002147053371184149}, {"date": "2021-09-22", "name": "Georgia", "id": "USA_US-GA", "total_count": 1, "lineage_count": 0, "cum_total_count": 6869, "cum_lineage_count": 5, "proportion": 0.0007279079924297568, "proportion_ci_lower": 0.0002778037893174362, "proportion_ci_upper": 0.0015948277409669753}, {"date": "2021-08-10", "name": "Guam", "id": "USA_US-None", "total_count": 8, "lineage_count": 0, "cum_total_count": 19, "cum_lineage_count": 0, "proportion": 0.0, "proportion_ci_lower": 2.5505812625695268e-05, "proportion_ci_upper": 0.12230940431991393}, {"date": "2021-09-10", "name": "Hawaii", "id": "USA_US-HI", "total_count": 1, "lineage_count": 0, "cum_total_count": 384, "cum_lineage_count": 0, "proportion": 0.0, "proportion_ci_lower": 1.2779027739184436e-06, "proportion_ci_upper": 0.0065159373526723395}, {"date": "2021-09-15", "name": "Idaho", "id": "USA_US-ID", "total_count": 1, "lineage_count": 0, "cum_total_count": 1613, "cum_lineage_count": 0, "proportion": 0.0, "proportion_ci_lower": 3.0437593550947587e-07, "proportion_ci_upper": 0.0015558582936217617}, {"date": "2021-09-20", "name": "Illinois", "id": "USA_US-IL", "total_count": 1, "lineage_count": 0, "cum_total_count": 3809, "cum_lineage_count": 2, "proportion": 0.0005250721974271463, "proportion_ci_lower": 0.00010912706267253706, "proportion_ci_upper": 0.0016834107953446198}, {"date": "2021-09-24", "name": "Indiana", "id": "USA_US-IN", "total_count": 4, "lineage_count": 0, "cum_total_count": 2726, "cum_lineage_count": 1, "proportion": 0.00036683785766691124, "proportion_ci_lower": 3.958378669661979e-05, "proportion_ci_upper": 0.0017133619928055843}, {"date": "2021-09-24", "name": "Iowa", "id": "USA_US-IA", "total_count": 4, "lineage_count": 0, "cum_total_count": 2246, "cum_lineage_count": 1, "proportion": 0.0004452359750667854, "proportion_ci_lower": 4.8044105768986664e-05, "proportion_ci_upper": 0.0020791900158607657}, {"date": "2021-08-09", "name": "KY", "id": "USA_US-None", "total_count": 5, "lineage_count": 0, "cum_total_count": 7, "cum_lineage_count": 0, "proportion": 0.0, "proportion_ci_lower": 6.768646424383031e-05, "proportion_ci_upper": 0.29243617366230995}, {"date": "2021-09-24", "name": "Kansas", "id": "USA_US-KS", "total_count": 11, "lineage_count": 0, "cum_total_count": 2360, "cum_lineage_count": 0, "proportion": 0.0, "proportion_ci_lower": 2.0804342961699553e-07, "proportion_ci_upper": 0.0010637037760145413}, {"date": "2021-09-17", "name": "Kentucky", "id": "USA_US-KY", "total_count": 16, "lineage_count": 0, "cum_total_count": 2960, "cum_lineage_count": 0, "proportion": 0.0, "proportion_ci_lower": 1.6587602942739252e-07, "proportion_ci_upper": 0.0008481978233972343}, {"date": "2021-09-23", "name": "Louisiana", "id": "USA_US-LA", "total_count": 3, "lineage_count": 0, "cum_total_count": 2581, "cum_lineage_count": 0, "proportion": 0.0, "proportion_ci_lower": 1.9023128700402588e-07, "proportion_ci_upper": 0.0009726764978260659}, {"date": "2021-09-20", "name": "Maine", "id": "USA_US-ME", "total_count": 6, "lineage_count": 0, "cum_total_count": 840, "cum_lineage_count": 4, "proportion": 0.004761904761904762, "proportion_ci_lower": 0.00160943614702193, "proportion_ci_upper": 0.011282618829810853}, {"date": "2021-09-17", "name": "Maryland", "id": "USA_US-MD", "total_count": 2, "lineage_count": 0, "cum_total_count": 4215, "cum_lineage_count": 6, "proportion": 0.0014234875444839859, "proportion_ci_lower": 0.00059436910060635, "proportion_ci_upper": 0.002931845568502789}, {"date": "2021-09-19", "name": "Massachusets", "id": "USA_US-None", "total_count": 3, "lineage_count": 0, "cum_total_count": 284, "cum_lineage_count": 0, "proportion": 0.0, "proportion_ci_lower": 1.7274721002136156e-06, "proportion_ci_upper": 0.008798149536904916}, {"date": "2021-09-21", "name": "Massachusetts", "id": "USA_US-MA", "total_count": 28, "lineage_count": 0, "cum_total_count": 16179, "cum_lineage_count": 6, "proportion": 0.0003708511032820323, "proportion_ci_lower": 0.0001548060537275456, "proportion_ci_upper": 0.0007642732935511098}, {"date": "2021-09-15", "name": "Michigan", "id": "USA_US-MI", "total_count": 1, "lineage_count": 0, "cum_total_count": 2255, "cum_lineage_count": 1, "proportion": 0.0004434589800443459, "proportion_ci_lower": 4.785233878143021e-05, "proportion_ci_upper": 0.002070899375319013}, {"date": "2021-09-20", "name": "Minnesota", "id": "USA_US-MN", "total_count": 1, "lineage_count": 0, "cum_total_count": 8607, "cum_lineage_count": 4, "proportion": 0.000464738003950273, "proportion_ci_lower": 0.000156891298745933, "proportion_ci_upper": 0.0011046895382936794}, {"date": "2021-09-15", "name": "Mississippi", "id": "USA_US-MS", "total_count": 3, "lineage_count": 0, "cum_total_count": 2333, "cum_lineage_count": 1, "proportion": 0.0004286326618088298, "proportion_ci_lower": 4.625234041830456e-05, "proportion_ci_upper": 0.0020017242039398475}, {"date": "2021-09-23", "name": "Missouri", "id": "USA_US-MO", "total_count": 2, "lineage_count": 0, "cum_total_count": 2505, "cum_lineage_count": 0, "proportion": 0.0, "proportion_ci_lower": 1.960021985908546e-07, "proportion_ci_upper": 0.0010021691064750029}, {"date": "2021-09-27", "name": "Montana", "id": "USA_US-MT", "total_count": 6, "lineage_count": 0, "cum_total_count": 994, "cum_lineage_count": 0, "proportion": 0.0, "proportion_ci_lower": 4.938741984466267e-07, "proportion_ci_upper": 0.002523281244776999}, {"date": "2021-09-26", "name": "Nebraska", "id": "USA_US-NE", "total_count": 2, "lineage_count": 0, "cum_total_count": 1986, "cum_lineage_count": 0, "proportion": 0.0, "proportion_ci_lower": 2.4721686293363133e-07, "proportion_ci_upper": 0.001263866746489861}, {"date": "2021-09-21", "name": "Nevada", "id": "USA_US-NV", "total_count": 16, "lineage_count": 0, "cum_total_count": 2654, "cum_lineage_count": 0, "proportion": 0.0, "proportion_ci_lower": 1.8499934481988205e-07, "proportion_ci_upper": 0.0009459375740026991}, {"date": "2021-09-21", "name": "New Hampshire", "id": "USA_US-NH", "total_count": 7, "lineage_count": 0, "cum_total_count": 689, "cum_lineage_count": 0, "proportion": 0.0, "proportion_ci_lower": 7.124183552654098e-07, "proportion_ci_upper": 0.003637824987422604}, {"date": "2021-09-18", "name": "New Jersey", "id": "USA_US-NJ", "total_count": 2, "lineage_count": 0, "cum_total_count": 4445, "cum_lineage_count": 2, "proportion": 0.0004499437570303712, "proportion_ci_lower": 9.351102654575377e-05, "proportion_ci_upper": 0.001442678020454502}, {"date": "2021-09-21", "name": "New Mexico", "id": "USA_US-NM", "total_count": 1, "lineage_count": 0, "cum_total_count": 1982, "cum_lineage_count": 0, "proportion": 0.0, "proportion_ci_lower": 2.477157239823463e-07, "proportion_ci_upper": 0.0012664154987962863}, {"date": "2021-09-22", "name": "New York", "id": "USA_US-NY", "total_count": 1, "lineage_count": 0, "cum_total_count": 10143, "cum_lineage_count": 7, "proportion": 0.0006901311249137336, "proportion_ci_lower": 0.0003087438664076451, "proportion_ci_upper": 0.0013545586896339668}, {"date": "2021-09-22", "name": "North Carolina", "id": "USA_US-NC", "total_count": 2, "lineage_count": 0, "cum_total_count": 7706, "cum_lineage_count": 3, "proportion": 0.0003893070334804049, "proportion_ci_lower": 0.00010965810317655526, "proportion_ci_upper": 0.0010386091491598748}, {"date": "2021-09-10", "name": "North Dakota", "id": "USA_US-ND", "total_count": 3, "lineage_count": 0, "cum_total_count": 651, "cum_lineage_count": 0, "proportion": 0.0, "proportion_ci_lower": 7.539874660707355e-07, "proportion_ci_upper": 0.0038496804640532666}, {"date": "2021-08-29", "name": "Northern Mariana Islands", "id": "USA_US-None", "total_count": 2, "lineage_count": 0, "cum_total_count": 18, "cum_lineage_count": 0, "proportion": 0.0, "proportion_ci_lower": 2.690311730090928e-05, "proportion_ci_upper": 0.12855821182175955}, {"date": "2021-09-21", "name": "Ohio", "id": "USA_US-OH", "total_count": 12, "lineage_count": 0, "cum_total_count": 4164, "cum_lineage_count": 5, "proportion": 0.0012007684918347744, "proportion_ci_lower": 0.0004583257169306476, "proportion_ci_upper": 0.0026300492991736535}, {"date": "2021-09-22", "name": "Oklahoma", "id": "USA_US-OK", "total_count": 1, "lineage_count": 0, "cum_total_count": 453, "cum_lineage_count": 0, "proportion": 0.0, "proportion_ci_lower": 1.0833628635070902e-06, "proportion_ci_upper": 0.005526738525141419}, {"date": "2021-09-18", "name": "Oregon", "id": "USA_US-OR", "total_count": 1, "lineage_count": 0, "cum_total_count": 3250, "cum_lineage_count": 24, "proportion": 0.0073846153846153844, "proportion_ci_lower": 0.004860386162322942, "proportion_ci_upper": 0.01078413965046654}, {"date": "2021-09-18", "name": "Pennsylvania", "id": "USA_US-PA", "total_count": 7, "lineage_count": 0, "cum_total_count": 2654, "cum_lineage_count": 0, "proportion": 0.0, "proportion_ci_lower": 1.8499934481988205e-07, "proportion_ci_upper": 0.0009459375740026991}, {"date": "2021-09-20", "name": "Rhode Island", "id": "USA_US-RI", "total_count": 9, "lineage_count": 0, "cum_total_count": 1536, "cum_lineage_count": 0, "proportion": 0.0, "proportion_ci_lower": 3.1963187867048475e-07, "proportion_ci_upper": 0.0016337773589523493}, {"date": "2021-09-15", "name": "South Carolina", "id": "USA_US-SC", "total_count": 1, "lineage_count": 0, "cum_total_count": 3378, "cum_lineage_count": 2, "proportion": 0.0005920663114268798, "proportion_ci_lower": 0.0001230528519936441, "proportion_ci_upper": 0.0018980413834615018}, {"date": "2021-09-21", "name": "South Dakota", "id": "USA_US-SD", "total_count": 7, "lineage_count": 0, "cum_total_count": 495, "cum_lineage_count": 0, "proportion": 0.0, "proportion_ci_lower": 9.914876377136772e-07, "proportion_ci_upper": 0.00505922790912572}, {"date": "2021-08-20", "name": "SouthCarolina", "id": "USA_US-None", "total_count": 1, "lineage_count": 0, "cum_total_count": 1, "cum_lineage_count": 0, "proportion": 0.0, "proportion_ci_lower": 0.00038558098075590136, "proportion_ci_upper": 0.8532536836904249}, {"date": "2021-09-21", "name": "Tennessee", "id": "USA_US-TN", "total_count": 2, "lineage_count": 0, "cum_total_count": 4715, "cum_lineage_count": 3, "proportion": 0.0006362672322375398, "proportion_ci_lower": 0.00017923285902430027, "proportion_ci_upper": 0.0016970749335272206}, {"date": "2021-09-22", "name": "Texas", "id": "USA_US-TX", "total_count": 33, "lineage_count": 0, "cum_total_count": 11673, "cum_lineage_count": 16, "proportion": 0.0013706844855649791, "proportion_ci_lower": 0.0008160515787689715, "proportion_ci_upper": 0.002171834601557676}, {"date": "2021-09-09", "name": "US Virgin Islands", "id": "USA_US-None", "total_count": 5, "lineage_count": 0, "cum_total_count": 65, "cum_lineage_count": 0, "proportion": 0.0, "proportion_ci_lower": 7.525350280859225e-06, "proportion_ci_upper": 0.037764885553982455}, {"date": "2021-09-09", "name": "Unknown", "id": "USA_US-None", "total_count": 1, "lineage_count": 0, "cum_total_count": 49, "cum_lineage_count": 0, "proportion": 0.0, "proportion_ci_lower": 9.970066657287018e-06, "proportion_ci_upper": 0.04972338528782203}, {"date": "2021-09-22", "name": "Utah", "id": "USA_US-UT", "total_count": 3, "lineage_count": 0, "cum_total_count": 4912, "cum_lineage_count": 0, "proportion": 0.0, "proportion_ci_lower": 9.996122620332601e-08, "proportion_ci_upper": 0.0005112323145171629}, {"date": "2021-09-21", "name": "Vermont", "id": "USA_US-VT", "total_count": 1, "lineage_count": 0, "cum_total_count": 2372, "cum_lineage_count": 0, "proportion": 0.0, "proportion_ci_lower": 2.0699104438469656e-07, "proportion_ci_upper": 0.0010583258908539231}, {"date": "2021-09-17", "name": "Virginia", "id": "USA_US-VA", "total_count": 1, "lineage_count": 0, "cum_total_count": 3257, "cum_lineage_count": 3, "proportion": 0.00092109303039607, "proportion_ci_lower": 0.0002594870629419643, "proportion_ci_upper": 0.0024561304555721364}, {"date": "2021-09-20", "name": "Washington", "id": "USA_US-WA", "total_count": 2, "lineage_count": 0, "cum_total_count": 8483, "cum_lineage_count": 23, "proportion": 0.0027113049628669102, "proportion_ci_lower": 0.0017664440846015673, "proportion_ci_upper": 0.003994755793933491}, {"date": "2021-09-19", "name": "West Virginia", "id": "USA_US-WV", "total_count": 1, "lineage_count": 0, "cum_total_count": 2873, "cum_lineage_count": 5, "proportion": 0.001740341106856944, "proportion_ci_lower": 0.0006643701657873219, "proportion_ci_upper": 0.003810549101376015}, {"date": "2021-09-21", "name": "Wisconsin", "id": "USA_US-WI", "total_count": 18, "lineage_count": 0, "cum_total_count": 2953, "cum_lineage_count": 1, "proportion": 0.0003386386725364037, "proportion_ci_lower": 3.654074020574567e-05, "proportion_ci_upper": 0.001581747253938337}, {"date": "2021-09-20", "name": "Wyoming", "id": "USA_US-WY", "total_count": 2, "lineage_count": 0, "cum_total_count": 2741, "cum_lineage_count": 0, "proportion": 0.0, "proportion_ci_lower": 1.7912795715862848e-07, "proportion_ci_upper": 0.0009159297795898007}]}}