{"success": true, "results": [{"date": "2021-07-15", "name": "Alabama", "id": "USA_US-AL", "total_count": 3, "lineage_count": 0, "cum_total_count": 262, "cum_lineage_count": 14, "proportion": 0.05343511450381679, "proportion_ci_lower": 0.030951304781218426, "proportion_ci_upper": 0.0856971462177959}, {"date": "2021-07-06", "name": "Alaska", "id": "USA_US-AK", "total_count": 3, "lineage_count": 0, "cum_total_count": 430, "cum_lineage_count": 34, "proportion": 0.07906976744186046, "proportion_ci_lower": 0.05636201300511531, "proportion_ci_upper": 0.1074167972854595}, {"date": "2021-07-07", "name": "Arizona", "id": "USA_US-AZ", "total_count": 5, "lineage_count": 1, "cum_total_count": 924, "cum_lineage_count": 180, "proportion": 0.19480519480519481, "proportion_ci_lower": 0.17024556972390412, "proportion_ci_upper": 0.22127321221372698}, {"date": "2021-07-01", "name": "Arkansas", "id": "USA_US-AR", "total_count": 7, "lineage_count": 0, "cum_total_count": 327, "cum_lineage_count": 6, "proportion": 0.01834862385321101, "proportion_ci_lower": 0.007694010522636652, "proportion_ci_upper": 0.03742611341753488}, {"date": "2021-07-07", "name": "California", "id": "USA_US-CA", "total_count": 1, "lineage_count": 0, "cum_total_count": 5123, "cum_lineage_count": 586, "proportion": 0.11438610189342183, "proportion_ci_lower": 0.10588876798788104, "proportion_ci_upper": 0.12331899012488856}, {"date": "2021-07-02", "name": "Colorado", "id": "USA_US-CO", "total_count": 4, "lineage_count": 0, "cum_total_count": 1983, "cum_lineage_count": 95, "proportion": 0.04790721129601614, "proportion_ci_lower": 0.0391582202355771, "proportion_ci_upper": 0.05797427959842216}, {"date": "2021-07-03", "name": "Connecticut", "id": "USA_US-CT", "total_count": 3, "lineage_count": 0, "cum_total_count": 267, "cum_lineage_count": 32, "proportion": 0.1198501872659176, "proportion_ci_lower": 0.08503126283507731, "proportion_ci_upper": 0.16285324846922422}, {"date": "2021-06-25", "name": "Delaware", "id": "USA_US-DE", "total_count": 1, "lineage_count": 0, "cum_total_count": 162, "cum_lineage_count": 9, "proportion": 0.05555555555555555, "proportion_ci_lower": 0.027840950251707217, "proportion_ci_upper": 0.09892586777680046}, {"date": "2021-06-30", "name": "District of Columbia", "id": "USA_US-DC", "total_count": 1, "lineage_count": 0, "cum_total_count": 101, "cum_lineage_count": 11, "proportion": 0.10891089108910891, "proportion_ci_lower": 0.05926175632391353, "proportion_ci_upper": 0.18055526029471547}, {"date": "2021-07-08", "name": "Florida", "id": "USA_US-FL", "total_count": 2, "lineage_count": 0, "cum_total_count": 2955, "cum_lineage_count": 573, "proportion": 0.19390862944162437, "proportion_ci_lower": 0.17995745401509486, "proportion_ci_upper": 0.20845906301619965}, {"date": "2021-06-30", "name": "Georgia", "id": "USA_US-GA", "total_count": 6, "lineage_count": 0, "cum_total_count": 455, "cum_lineage_count": 45, "proportion": 0.0989010989010989, "proportion_ci_lower": 0.07401362167864714, "proportion_ci_upper": 0.12886957304229874}, {"date": "2021-05-28", "name": "Guam", "id": "USA_US-None", "total_count": 1, "lineage_count": 0, "cum_total_count": 3, "cum_lineage_count": 0, "proportion": 0.0, "proportion_ci_lower": 0.00015063602543656854, "proportion_ci_upper": 0.5355832430429506}, {"date": "2021-06-28", "name": "Hawaii", "id": "USA_US-HI", "total_count": 1, "lineage_count": 1, "cum_total_count": 227, "cum_lineage_count": 51, "proportion": 0.22466960352422907, "proportion_ci_lower": 0.17408082450477025, "proportion_ci_upper": 0.28222716832045747}, {"date": "2021-06-24", "name": "Idaho", "id": "USA_US-ID", "total_count": 2, "lineage_count": 0, "cum_total_count": 195, "cum_lineage_count": 26, "proportion": 0.13333333333333333, "proportion_ci_lower": 0.09112315596974209, "proportion_ci_upper": 0.18632625864876973}, {"date": "2021-07-12", "name": "Illinois", "id": "USA_US-IL", "total_count": 1, "lineage_count": 0, "cum_total_count": 1122, "cum_lineage_count": 162, "proportion": 0.1443850267379679, "proportion_ci_lower": 0.12474478477407033, "proportion_ci_upper": 0.1658569994415494}, {"date": "2021-07-12", "name": "Indiana", "id": "USA_US-IN", "total_count": 4, "lineage_count": 0, "cum_total_count": 751, "cum_lineage_count": 68, "proportion": 0.09054593874833555, "proportion_ci_lower": 0.07159312096524133, "proportion_ci_upper": 0.11264638914032066}, {"date": "2021-07-08", "name": "Iowa", "id": "USA_US-IA", "total_count": 1, "lineage_count": 0, "cum_total_count": 65, "cum_lineage_count": 9, "proportion": 0.13846153846153847, "proportion_ci_lower": 0.07078036694677539, "proportion_ci_upper": 0.23745300017782045}, {"date": "2021-07-13", "name": "Kansas", "id": "USA_US-KS", "total_count": 1, "lineage_count": 0, "cum_total_count": 1106, "cum_lineage_count": 78, "proportion": 0.0705244122965642, "proportion_ci_lower": 0.0565487648468131, "proportion_ci_upper": 0.08674350553589305}, {"date": "2021-07-06", "name": "Kentucky", "id": "USA_US-KY", "total_count": 1, "lineage_count": 0, "cum_total_count": 244, "cum_lineage_count": 19, "proportion": 0.0778688524590164, "proportion_ci_lower": 0.049155507302656366, "proportion_ci_upper": 0.1165117720524893}, {"date": "2021-07-05", "name": "Louisiana", "id": "USA_US-LA", "total_count": 1, "lineage_count": 0, "cum_total_count": 516, "cum_lineage_count": 21, "proportion": 0.040697674418604654, "proportion_ci_lower": 0.026136393159240493, "proportion_ci_upper": 0.06038534988285593}, {"date": "2021-06-28", "name": "Maine", "id": "USA_US-ME", "total_count": 1, "lineage_count": 0, "cum_total_count": 222, "cum_lineage_count": 3, "proportion": 0.013513513513513514, "proportion_ci_lower": 0.003820291044892153, "proportion_ci_upper": 0.035620096650543}, {"date": "2021-07-07", "name": "Maryland", "id": "USA_US-MD", "total_count": 4, "lineage_count": 0, "cum_total_count": 528, "cum_lineage_count": 26, "proportion": 0.04924242424242424, "proportion_ci_lower": 0.033189827576000155, "proportion_ci_upper": 0.07021411923981691}, {"date": "2021-06-29", "name": "Massachusetts", "id": "USA_US-MA", "total_count": 2, "lineage_count": 0, "cum_total_count": 295, "cum_lineage_count": 58, "proportion": 0.19661016949152543, "proportion_ci_lower": 0.15434408279963274, "proportion_ci_upper": 0.24479479643507862}, {"date": "2021-06-26", "name": "Michigan", "id": "USA_US-MI", "total_count": 2, "lineage_count": 0, "cum_total_count": 185, "cum_lineage_count": 10, "proportion": 0.05405405405405406, "proportion_ci_lower": 0.028126642561566766, "proportion_ci_upper": 0.0937597428114687}, {"date": "2021-07-08", "name": "Minnesota", "id": "USA_US-MN", "total_count": 3, "lineage_count": 1, "cum_total_count": 1256, "cum_lineage_count": 105, "proportion": 0.08359872611464968, "proportion_ci_lower": 0.06924635099289378, "proportion_ci_upper": 0.09986708110964304}, {"date": "2021-07-07", "name": "Mississippi", "id": "USA_US-MS", "total_count": 1, "lineage_count": 0, "cum_total_count": 363, "cum_lineage_count": 9, "proportion": 0.024793388429752067, "proportion_ci_lower": 0.012337041172862126, "proportion_ci_upper": 0.04475803893630115}, {"date": "2021-06-29", "name": "Missouri", "id": "USA_US-MO", "total_count": 20, "lineage_count": 0, "cum_total_count": 974, "cum_lineage_count": 14, "proportion": 0.014373716632443531, "proportion_ci_lower": 0.008261009858847052, "proportion_ci_upper": 0.023358604317875065}, {"date": "2021-07-12", "name": "Montana", "id": "USA_US-MT", "total_count": 2, "lineage_count": 0, "cum_total_count": 377, "cum_lineage_count": 18, "proportion": 0.04774535809018567, "proportion_ci_lower": 0.029573255725484894, "proportion_ci_upper": 0.07281645190857067}, {"date": "2021-07-12", "name": "Nebraska", "id": "USA_US-NE", "total_count": 6, "lineage_count": 0, "cum_total_count": 326, "cum_lineage_count": 41, "proportion": 0.12576687116564417, "proportion_ci_lower": 0.09311813707384255, "proportion_ci_upper": 0.1650229758790126}, {"date": "2021-07-08", "name": "Nevada", "id": "USA_US-NV", "total_count": 1, "lineage_count": 0, "cum_total_count": 1429, "cum_lineage_count": 75, "proportion": 0.052484254723582924, "proportion_ci_lower": 0.041815611131649645, "proportion_ci_upper": 0.06496269322153014}, {"date": "2021-06-26", "name": "New Hampshire", "id": "USA_US-NH", "total_count": 1, "lineage_count": 1, "cum_total_count": 78, "cum_lineage_count": 13, "proportion": 0.16666666666666666, "proportion_ci_lower": 0.09677309492641781, "proportion_ci_upper": 0.2607454870230105}, {"date": "2021-07-03", "name": "New Jersey", "id": "USA_US-NJ", "total_count": 1, "lineage_count": 0, "cum_total_count": 998, "cum_lineage_count": 76, "proportion": 0.07615230460921844, "proportion_ci_lower": 0.06091553796935839, "proportion_ci_upper": 0.0938423205497666}, {"date": "2021-07-07", "name": "New Mexico", "id": "USA_US-NM", "total_count": 1, "lineage_count": 0, "cum_total_count": 417, "cum_lineage_count": 19, "proportion": 0.045563549160671464, "proportion_ci_lower": 0.02859350676681545, "proportion_ci_upper": 0.06880410989684105}, {"date": "2021-07-06", "name": "New York", "id": "USA_US-NY", "total_count": 9, "lineage_count": 0, "cum_total_count": 1168, "cum_lineage_count": 124, "proportion": 0.10616438356164383, "proportion_ci_lower": 0.08947468192234523, "proportion_ci_upper": 0.12480272447023144}, {"date": "2021-07-01", "name": "North Carolina", "id": "USA_US-NC", "total_count": 2, "lineage_count": 0, "cum_total_count": 831, "cum_lineage_count": 60, "proportion": 0.07220216606498195, "proportion_ci_lower": 0.056078968105913944, "proportion_ci_upper": 0.09129770936656811}, {"date": "2021-06-30", "name": "North Dakota", "id": "USA_US-ND", "total_count": 1, "lineage_count": 0, "cum_total_count": 302, "cum_lineage_count": 9, "proportion": 0.029801324503311258, "proportion_ci_lower": 0.01484595624011481, "proportion_ci_upper": 0.05367911979505835}, {"date": "2021-07-15", "name": "Ohio", "id": "USA_US-OH", "total_count": 13, "lineage_count": 1, "cum_total_count": 738, "cum_lineage_count": 92, "proportion": 0.12466124661246612, "proportion_ci_lower": 0.1023088206773455, "proportion_ci_upper": 0.14995029304214214}, {"date": "2021-07-08", "name": "Oklahoma", "id": "USA_US-OK", "total_count": 1, "lineage_count": 0, "cum_total_count": 70, "cum_lineage_count": 4, "proportion": 0.05714285714285714, "proportion_ci_lower": 0.01959283371629736, "proportion_ci_upper": 0.130143024165157}, {"date": "2021-07-09", "name": "Oregon", "id": "USA_US-OR", "total_count": 1, "lineage_count": 0, "cum_total_count": 768, "cum_lineage_count": 163, "proportion": 0.21223958333333334, "proportion_ci_lower": 0.18443641711790568, "proportion_ci_upper": 0.2422068525887967}, {"date": "2021-06-29", "name": "Pennsylvania", "id": "USA_US-PA", "total_count": 1, "lineage_count": 0, "cum_total_count": 398, "cum_lineage_count": 25, "proportion": 0.06281407035175879, "proportion_ci_lower": 0.0420850002107096, "proportion_ci_upper": 0.08986625018599192}, {"date": "2021-06-26", "name": "Rhode Island", "id": "USA_US-RI", "total_count": 1, "lineage_count": 0, "cum_total_count": 203, "cum_lineage_count": 26, "proportion": 0.12807881773399016, "proportion_ci_lower": 0.08745431421898145, "proportion_ci_upper": 0.179212724678684}, {"date": "2021-06-29", "name": "South Carolina", "id": "USA_US-SC", "total_count": 3, "lineage_count": 0, "cum_total_count": 250, "cum_lineage_count": 14, "proportion": 0.056, "proportion_ci_lower": 0.032453806982567154, "proportion_ci_upper": 0.08973214979300437}, {"date": "2021-06-18", "name": "South Dakota", "id": "USA_US-SD", "total_count": 1, "lineage_count": 0, "cum_total_count": 22, "cum_lineage_count": 0, "proportion": 0.0, "proportion_ci_lower": 2.2067332398350842e-05, "proportion_ci_upper": 0.10673971791178566}, {"date": "2021-07-04", "name": "Tennessee", "id": "USA_US-TN", "total_count": 1, "lineage_count": 0, "cum_total_count": 271, "cum_lineage_count": 29, "proportion": 0.1070110701107011, "proportion_ci_lower": 0.0743956785294556, "proportion_ci_upper": 0.14796157319560355}, {"date": "2021-07-07", "name": "Texas", "id": "USA_US-TX", "total_count": 20, "lineage_count": 0, "cum_total_count": 2687, "cum_lineage_count": 204, "proportion": 0.07592110160029773, "proportion_ci_lower": 0.06636087242377302, "proportion_ci_upper": 0.08639421202075148}, {"date": "2021-06-14", "name": "Unknown", "id": "USA_US-None", "total_count": 2, "lineage_count": 0, "cum_total_count": 15, "cum_lineage_count": 4, "proportion": 0.26666666666666666, "proportion_ci_lower": 0.09741092580268484, "proportion_ci_upper": 0.5166215050118868}, {"date": "2021-06-30", "name": "Utah", "id": "USA_US-UT", "total_count": 2, "lineage_count": 0, "cum_total_count": 1951, "cum_lineage_count": 32, "proportion": 0.016401845207585853, "proportion_ci_lower": 0.011457909949931813, "proportion_ci_upper": 0.022777430427237122}, {"date": "2021-06-29", "name": "Vermont", "id": "USA_US-VT", "total_count": 2, "lineage_count": 0, "cum_total_count": 8, "cum_lineage_count": 0, "proportion": 0.0, "proportion_ci_lower": 5.949030289440227e-05, "proportion_ci_upper": 0.26221724871718577}, {"date": "2021-05-30", "name": "Virgin Islands", "id": "USA_US-None", "total_count": 1, "lineage_count": 0, "cum_total_count": 1, "cum_lineage_count": 0, "proportion": 0.0, "proportion_ci_lower": 0.00038558098075590136, "proportion_ci_upper": 0.8532536836904249}, {"date": "2021-05-26", "name": "Virgin Islands of the U.S.", "id": "USA_US-None", "total_count": 1, "lineage_count": 0, "cum_total_count": 2, "cum_lineage_count": 0, "proportion": 0.0, "proportion_ci_lower": 0.00021690847003096627, "proportion_ci_upper": 0.6668217544012093}, {"date": "2021-07-06", "name": "Virginia", "id": "USA_US-VA", "total_count": 1, "lineage_count": 0, "cum_total_count": 568, "cum_lineage_count": 49, "proportion": 0.08626760563380281, "proportion_ci_lower": 0.06527106959690697, "proportion_ci_upper": 0.1114655842281177}, {"date": "2021-07-07", "name": "Washington", "id": "USA_US-WA", "total_count": 34, "lineage_count": 2, "cum_total_count": 3225, "cum_lineage_count": 560, "proportion": 0.17364341085271318, "proportion_ci_lower": 0.16086546718494993, "proportion_ci_upper": 0.18700681915072837}, {"date": "2021-06-25", "name": "West Virginia", "id": "USA_US-WV", "total_count": 5, "lineage_count": 0, "cum_total_count": 391, "cum_lineage_count": 7, "proportion": 0.017902813299232736, "proportion_ci_lower": 0.00804262099602234, "proportion_ci_upper": 0.03482654338883873}, {"date": "2021-07-06", "name": "Wisconsin", "id": "USA_US-WI", "total_count": 4, "lineage_count": 0, "cum_total_count": 429, "cum_lineage_count": 42, "proportion": 0.0979020979020979, "proportion_ci_lower": 0.07248214134736637, "proportion_ci_upper": 0.1287229472108613}, {"date": "2021-07-07", "name": "Wyoming", "id": "USA_US-WY", "total_count": 5, "lineage_count": 0, "cum_total_count": 631, "cum_lineage_count": 27, "proportion": 0.042789223454833596, "proportion_ci_lower": 0.029034371358080697, "proportion_ci_upper": 0.06072133016799863}]}