{"success": true, "results": [{"date": "2021-03-15", "name": "Ae", "id": "USA_US-None", "total_count": 1, "lineage_count": 0, "cum_total_count": 1, "cum_lineage_count": 0, "proportion": 0.0, "proportion_ci_lower": 0.00038558098075590136, "proportion_ci_upper": 0.8532536836904249}, {"date": "2021-04-12", "name": "Alabama", "id": "USA_US-AL", "total_count": 4, "lineage_count": 0, "cum_total_count": 270, "cum_lineage_count": 5, "proportion": 0.018518518518518517, "proportion_ci_lower": 0.00710040913414597, "proportion_ci_upper": 0.04010912052388371}, {"date": "2021-04-15", "name": "Alaska", "id": "USA_US-AK", "total_count": 2, "lineage_count": 0, "cum_total_count": 419, "cum_lineage_count": 3, "proportion": 0.007159904534606206, "proportion_ci_lower": 0.002020546692087258, "proportion_ci_upper": 0.01898313697318954}, {"date": "2021-04-15", "name": "Arizona", "id": "USA_US-AZ", "total_count": 2, "lineage_count": 0, "cum_total_count": 1892, "cum_lineage_count": 22, "proportion": 0.011627906976744186, "proportion_ci_lower": 0.007510899755674778, "proportion_ci_upper": 0.01723475991226142}, {"date": "2021-04-08", "name": "Arkansas", "id": "USA_US-AR", "total_count": 2, "lineage_count": 0, "cum_total_count": 118, "cum_lineage_count": 1, "proportion": 0.00847457627118644, "proportion_ci_lower": 0.0009159120509720696, "proportion_ci_upper": 0.038918829778516684}, {"date": "2021-04-13", "name": "California", "id": "USA_US-CA", "total_count": 117, "lineage_count": 10, "cum_total_count": 10994, "cum_lineage_count": 363, "proportion": 0.03301800982354011, "proportion_ci_lower": 0.029799872375780464, "proportion_ci_upper": 0.036481959911764394}, {"date": "2021-04-13", "name": "Colorado", "id": "USA_US-CO", "total_count": 5, "lineage_count": 0, "cum_total_count": 3887, "cum_lineage_count": 27, "proportion": 0.006946231026498585, "proportion_ci_lower": 0.004687043480860001, "proportion_ci_upper": 0.009938134551324418}, {"date": "2021-04-12", "name": "Connecticut", "id": "USA_US-CT", "total_count": 1, "lineage_count": 0, "cum_total_count": 2202, "cum_lineage_count": 14, "proportion": 0.006357856494096276, "proportion_ci_lower": 0.003648291912908598, "proportion_ci_upper": 0.010359922271714672}, {"date": "2021-04-08", "name": "Delaware", "id": "USA_US-DE", "total_count": 1, "lineage_count": 0, "cum_total_count": 310, "cum_lineage_count": 5, "proportion": 0.016129032258064516, "proportion_ci_lower": 0.006180354265839269, "proportion_ci_upper": 0.034987894937538844}, {"date": "2021-04-13", "name": "District of Columbia", "id": "USA_US-DC", "total_count": 3, "lineage_count": 0, "cum_total_count": 173, "cum_lineage_count": 3, "proportion": 0.017341040462427744, "proportion_ci_lower": 0.004907572115618417, "proportion_ci_upper": 0.045548595174192075}, {"date": "2021-04-19", "name": "Florida", "id": "USA_US-FL", "total_count": 1, "lineage_count": 0, "cum_total_count": 9571, "cum_lineage_count": 340, "proportion": 0.035523978685612786, "proportion_ci_lower": 0.03195497293038148, "proportion_ci_upper": 0.039373820785122415}, {"date": "2021-03-10", "name": "GA", "id": "USA_US-None", "total_count": 1, "lineage_count": 0, "cum_total_count": 1, "cum_lineage_count": 0, "proportion": 0.0, "proportion_ci_lower": 0.00038558098075590136, "proportion_ci_upper": 0.8532536836904249}, {"date": "2021-04-13", "name": "Georgia", "id": "USA_US-GA", "total_count": 2, "lineage_count": 0, "cum_total_count": 1865, "cum_lineage_count": 16, "proportion": 0.008579088471849867, "proportion_ci_lower": 0.005114553349621982, "proportion_ci_upper": 0.013563252900299805}, {"date": "2021-04-12", "name": "Hawaii", "id": "USA_US-HI", "total_count": 1, "lineage_count": 0, "cum_total_count": 282, "cum_lineage_count": 0, "proportion": 0.0, "proportion_ci_lower": 1.7397128034676024e-06, "proportion_ci_upper": 0.008860215359773141}, {"date": "2021-04-09", "name": "Idaho", "id": "USA_US-ID", "total_count": 1, "lineage_count": 0, "cum_total_count": 362, "cum_lineage_count": 1, "proportion": 0.0027624309392265192, "proportion_ci_lower": 0.0002982214142596243, "proportion_ci_upper": 0.01283797882897908}, {"date": "2021-04-15", "name": "Illinois", "id": "USA_US-IL", "total_count": 1, "lineage_count": 0, "cum_total_count": 4059, "cum_lineage_count": 615, "proportion": 0.15151515151515152, "proportion_ci_lower": 0.14073482079999164, "proportion_ci_upper": 0.16279224306295137}, {"date": "2021-04-12", "name": "Indiana", "id": "USA_US-IN", "total_count": 11, "lineage_count": 1, "cum_total_count": 1736, "cum_lineage_count": 36, "proportion": 0.020737327188940093, "proportion_ci_lower": 0.014807486574190431, "proportion_ci_upper": 0.02826180942701384}, {"date": "2021-04-12", "name": "Iowa", "id": "USA_US-IA", "total_count": 1, "lineage_count": 0, "cum_total_count": 258, "cum_lineage_count": 2, "proportion": 0.007751937984496124, "proportion_ci_lower": 0.0016142732805767433, "proportion_ci_upper": 0.02463344854330274}, {"date": "2021-04-21", "name": "Kansas", "id": "USA_US-KS", "total_count": 6, "lineage_count": 0, "cum_total_count": 500, "cum_lineage_count": 10, "proportion": 0.02, "proportion_ci_lower": 0.010328096188075854, "proportion_ci_upper": 0.035186874061648554}, {"date": "2021-04-07", "name": "Kentucky", "id": "USA_US-KY", "total_count": 2, "lineage_count": 0, "cum_total_count": 582, "cum_lineage_count": 5, "proportion": 0.00859106529209622, "proportion_ci_lower": 0.003285463072203329, "proportion_ci_upper": 0.01872734958245248}, {"date": "2021-04-15", "name": "Las Vegas", "id": "USA_US-None", "total_count": 1, "lineage_count": 0, "cum_total_count": 19, "cum_lineage_count": 4, "proportion": 0.21052631578947367, "proportion_ci_lower": 0.07553185291347161, "proportion_ci_upper": 0.4262058677086049}, {"date": "2021-04-12", "name": "Louisiana", "id": "USA_US-LA", "total_count": 3, "lineage_count": 0, "cum_total_count": 348, "cum_lineage_count": 0, "proportion": 0.0, "proportion_ci_lower": 1.4100045537400306e-06, "proportion_ci_upper": 0.007187088981208038}, {"date": "2021-04-09", "name": "Maine", "id": "USA_US-ME", "total_count": 2, "lineage_count": 1, "cum_total_count": 676, "cum_lineage_count": 7, "proportion": 0.010355029585798817, "proportion_ci_lower": 0.0046433529126125375, "proportion_ci_upper": 0.0202228626172275}, {"date": "2021-04-19", "name": "Maryland", "id": "USA_US-MD", "total_count": 2, "lineage_count": 0, "cum_total_count": 3614, "cum_lineage_count": 20, "proportion": 0.005534034311012728, "proportion_ci_lower": 0.0034917839832089674, "proportion_ci_upper": 0.008366107264026978}, {"date": "2021-04-13", "name": "Massachusetts", "id": "USA_US-MA", "total_count": 3, "lineage_count": 1, "cum_total_count": 4002, "cum_lineage_count": 266, "proportion": 0.06646676661669165, "proportion_ci_lower": 0.05906117410750831, "proportion_ci_upper": 0.07449909205811289}, {"date": "2021-04-13", "name": "Michigan", "id": "USA_US-MI", "total_count": 5, "lineage_count": 0, "cum_total_count": 6938, "cum_lineage_count": 70, "proportion": 0.010089362928797925, "proportion_ci_lower": 0.007937091907285226, "proportion_ci_upper": 0.012650022123534166}, {"date": "2021-04-16", "name": "Minnesota", "id": "USA_US-MN", "total_count": 3, "lineage_count": 0, "cum_total_count": 5536, "cum_lineage_count": 37, "proportion": 0.006683526011560694, "proportion_ci_lower": 0.004785947280881472, "proportion_ci_upper": 0.00909614076347487}, {"date": "2021-04-13", "name": "Mississippi", "id": "USA_US-MS", "total_count": 3, "lineage_count": 0, "cum_total_count": 298, "cum_lineage_count": 2, "proportion": 0.006711409395973154, "proportion_ci_lower": 0.001397196124425512, "proportion_ci_upper": 0.02135422049865643}, {"date": "2021-04-12", "name": "Missouri", "id": "USA_US-MO", "total_count": 2, "lineage_count": 0, "cum_total_count": 514, "cum_lineage_count": 3, "proportion": 0.005836575875486381, "proportion_ci_lower": 0.0016464955565263703, "proportion_ci_upper": 0.015493392646876769}, {"date": "2021-04-08", "name": "Montana", "id": "USA_US-MT", "total_count": 3, "lineage_count": 0, "cum_total_count": 206, "cum_lineage_count": 0, "proportion": 0.0, "proportion_ci_lower": 2.380769033832878e-06, "proportion_ci_upper": 0.012105229107225965}, {"date": "2021-04-20", "name": "Nebraska", "id": "USA_US-NE", "total_count": 2, "lineage_count": 0, "cum_total_count": 348, "cum_lineage_count": 7, "proportion": 0.020114942528735632, "proportion_ci_lower": 0.009041263746178179, "proportion_ci_upper": 0.039084843634117905}, {"date": "2021-04-19", "name": "Nevada", "id": "USA_US-NV", "total_count": 5, "lineage_count": 0, "cum_total_count": 554, "cum_lineage_count": 5, "proportion": 0.009025270758122744, "proportion_ci_lower": 0.0034519060990453594, "proportion_ci_upper": 0.01966833130472212}, {"date": "2021-04-11", "name": "New Hampshire", "id": "USA_US-NH", "total_count": 1, "lineage_count": 1, "cum_total_count": 586, "cum_lineage_count": 22, "proportion": 0.03754266211604096, "proportion_ci_lower": 0.024356489862486144, "proportion_ci_upper": 0.055275882268515764}, {"date": "2021-04-17", "name": "New Jersey", "id": "USA_US-NJ", "total_count": 11, "lineage_count": 0, "cum_total_count": 5616, "cum_lineage_count": 91, "proportion": 0.016203703703703703, "proportion_ci_lower": 0.013145817828394366, "proportion_ci_upper": 0.019759867260367048}, {"date": "2021-04-12", "name": "New Mexico", "id": "USA_US-NM", "total_count": 1, "lineage_count": 0, "cum_total_count": 589, "cum_lineage_count": 3, "proportion": 0.0050933786078098476, "proportion_ci_lower": 0.0014365443007344544, "proportion_ci_upper": 0.013529777751315364}, {"date": "2021-04-22", "name": "New York", "id": "USA_US-NY", "total_count": 53, "lineage_count": 0, "cum_total_count": 15296, "cum_lineage_count": 202, "proportion": 0.013206066945606694, "proportion_ci_lower": 0.011487808988424032, "proportion_ci_upper": 0.015108486339007188}, {"date": "2021-04-15", "name": "North Carolina", "id": "USA_US-NC", "total_count": 2, "lineage_count": 0, "cum_total_count": 2199, "cum_lineage_count": 13, "proportion": 0.005911778080945885, "proportion_ci_lower": 0.0033175759949589535, "proportion_ci_upper": 0.009801084262508253}, {"date": "2021-04-08", "name": "North Dakota", "id": "USA_US-ND", "total_count": 3, "lineage_count": 0, "cum_total_count": 261, "cum_lineage_count": 1, "proportion": 0.0038314176245210726, "proportion_ci_lower": 0.0004137120103575553, "proportion_ci_upper": 0.017766313580042215}, {"date": "2021-03-18", "name": "North Dalota", "id": "USA_US-None", "total_count": 1, "lineage_count": 0, "cum_total_count": 1, "cum_lineage_count": 0, "proportion": 0.0, "proportion_ci_lower": 0.00038558098075590136, "proportion_ci_upper": 0.8532536836904249}, {"date": "2021-04-15", "name": "Ohio", "id": "USA_US-OH", "total_count": 193, "lineage_count": 8, "cum_total_count": 2624, "cum_lineage_count": 42, "proportion": 0.01600609756097561, "proportion_ci_lower": 0.011721776654706468, "proportion_ci_upper": 0.021356329427873688}, {"date": "2021-04-13", "name": "Oklahoma", "id": "USA_US-OK", "total_count": 1, "lineage_count": 0, "cum_total_count": 130, "cum_lineage_count": 0, "proportion": 0.0, "proportion_ci_lower": 3.7699249767690984e-06, "proportion_ci_upper": 0.019100681880484}, {"date": "2021-04-09", "name": "Oregon", "id": "USA_US-OR", "total_count": 3, "lineage_count": 0, "cum_total_count": 690, "cum_lineage_count": 13, "proportion": 0.01884057971014493, "proportion_ci_lower": 0.010600624429777947, "proportion_ci_upper": 0.031094068761495786}, {"date": "2021-04-16", "name": "Pennsylvania", "id": "USA_US-PA", "total_count": 1, "lineage_count": 0, "cum_total_count": 4856, "cum_lineage_count": 49, "proportion": 0.010090609555189456, "proportion_ci_lower": 0.0075628778675396946, "proportion_ci_upper": 0.013201602916997457}, {"date": "2021-04-08", "name": "Puerto Rico", "id": "USA_US-None", "total_count": 1, "lineage_count": 0, "cum_total_count": 217, "cum_lineage_count": 2, "proportion": 0.009216589861751152, "proportion_ci_lower": 0.001920040979087631, "proportion_ci_upper": 0.029235057811005327}, {"date": "2021-04-10", "name": "Rhode Island", "id": "USA_US-RI", "total_count": 5, "lineage_count": 0, "cum_total_count": 976, "cum_lineage_count": 22, "proportion": 0.022540983606557378, "proportion_ci_lower": 0.014586780897122632, "proportion_ci_upper": 0.033316683115437784}, {"date": "2021-04-10", "name": "South Carolina", "id": "USA_US-SC", "total_count": 1, "lineage_count": 0, "cum_total_count": 355, "cum_lineage_count": 6, "proportion": 0.016901408450704224, "proportion_ci_lower": 0.007084569610184711, "proportion_ci_upper": 0.0345028743174467}, {"date": "2021-04-06", "name": "South Dakota", "id": "USA_US-SD", "total_count": 2, "lineage_count": 0, "cum_total_count": 167, "cum_lineage_count": 1, "proportion": 0.005988023952095809, "proportion_ci_lower": 0.0006468542805609439, "proportion_ci_upper": 0.027642113100770027}, {"date": "2021-04-12", "name": "Tennessee", "id": "USA_US-TN", "total_count": 9, "lineage_count": 0, "cum_total_count": 1263, "cum_lineage_count": 8, "proportion": 0.006334125098970704, "proportion_ci_lower": 0.0029989510539414773, "proportion_ci_upper": 0.01191618596572408}, {"date": "2021-04-17", "name": "Texas", "id": "USA_US-TX", "total_count": 6, "lineage_count": 0, "cum_total_count": 5728, "cum_lineage_count": 63, "proportion": 0.010998603351955308, "proportion_ci_lower": 0.008538349256752223, "proportion_ci_upper": 0.013952537783416763}, {"date": "2021-04-10", "name": "Unknown", "id": "USA_US-None", "total_count": 12, "lineage_count": 0, "cum_total_count": 41, "cum_lineage_count": 0, "proportion": 0.0, "proportion_ci_lower": 1.1903578569170632e-05, "proportion_ci_upper": 0.05907570990931319}, {"date": "2021-04-13", "name": "Utah", "id": "USA_US-UT", "total_count": 1, "lineage_count": 0, "cum_total_count": 371, "cum_lineage_count": 5, "proportion": 0.013477088948787063, "proportion_ci_lower": 0.005160594065933727, "proportion_ci_upper": 0.029285437488653643}, {"date": "2021-04-10", "name": "Vermont", "id": "USA_US-VT", "total_count": 1, "lineage_count": 0, "cum_total_count": 296, "cum_lineage_count": 3, "proportion": 0.010135135135135136, "proportion_ci_lower": 0.0028625278890858303, "proportion_ci_upper": 0.026798090025721977}, {"date": "2021-04-16", "name": "Virginia", "id": "USA_US-VA", "total_count": 7, "lineage_count": 0, "cum_total_count": 1559, "cum_lineage_count": 3, "proportion": 0.001924310455420141, "proportion_ci_lower": 0.0005422601035352457, "proportion_ci_upper": 0.005126526323431357}, {"date": "2021-04-14", "name": "Washington", "id": "USA_US-WA", "total_count": 41, "lineage_count": 9, "cum_total_count": 4834, "cum_lineage_count": 227, "proportion": 0.04695904013239553, "proportion_ci_lower": 0.04126435251192752, "proportion_ci_upper": 0.05319595650236808}, {"date": "2021-04-13", "name": "West Virginia", "id": "USA_US-WV", "total_count": 1, "lineage_count": 0, "cum_total_count": 1317, "cum_lineage_count": 3, "proportion": 0.002277904328018223, "proportion_ci_lower": 0.0006419636133990131, "proportion_ci_upper": 0.006066561208810883}, {"date": "2021-04-13", "name": "Wisconsin", "id": "USA_US-WI", "total_count": 3, "lineage_count": 0, "cum_total_count": 2317, "cum_lineage_count": 30, "proportion": 0.01294777729823047, "proportion_ci_lower": 0.008930163443135557, "proportion_ci_upper": 0.018179530868458582}, {"date": "2021-04-12", "name": "Wyoming", "id": "USA_US-WY", "total_count": 2, "lineage_count": 0, "cum_total_count": 314, "cum_lineage_count": 1, "proportion": 0.0031847133757961785, "proportion_ci_lower": 0.00034383792873126756, "proportion_ci_upper": 0.014787452643259535}]}